setup.py
nomunkhet_rpi/__init__.py
nomunkhet_rpi/arrowD.py
nomunkhet_rpi/arrowU.py
nomunkhet_rpi/eslogo.py
nomunkhet_rpi/lamp.py
nomunkhet_rpi/lamp1.py
nomunkhet_rpi.egg-info/PKG-INFO
nomunkhet_rpi.egg-info/SOURCES.txt
nomunkhet_rpi.egg-info/dependency_links.txt
nomunkhet_rpi.egg-info/not-zip-safe
nomunkhet_rpi.egg-info/top_level.txt