Metadata-Version: 1.0
Name: nomunkhet-rpi
Version: 0.7.2.11
Summary: Тус сан нь Номун хэт ХХК-н Электроникийн сургалтын "Raspberry Pi-д суурилсан IoT хөгжүүлэх сургалт"-д зориулагдсан болно.
Home-page: http://elecbook.net
Author: Garid
Author-email: garidzorigoo@gmail.com
License: MIT
Platform: UNKNOWN
